bodo_magic/__init__.py
bodo_magic/_version.py
bodo_magic/utils.py
bodo_magic-1.1.0.dist-info/LICENSE
bodo_magic-1.1.0.dist-info/METADATA
bodo_magic-1.1.0.dist-info/WHEEL
bodo_magic-1.1.0.dist-info/top_level.txt
bodo_magic-1.1.0.dist-info/RECORD
