Metadata-Version: 2.1
Name: bodo-magic
Version: 1.1.0
Summary: IPython Magic for Writing Simpler Bodo Code
Home-page: https://github.com/Bodo-inc/bodo-magic
Author: Srinivas Lade
Author-email: 
License: UNKNOWN
Platform: UNKNOWN
Classifier: Programming Language :: Python :: 3
Classifier: Operating System :: OS Independent
Requires-Python: >3.7
License-File: LICENSE
Requires-Dist: numba (>=0.53.0)
Requires-Dist: IPython
